groupdocs/__init__.py
groupdocs/merger.cpython-310-darwin.so
groupdocs/merger.cpython-311-darwin.so
groupdocs/merger.cpython-312-darwin.so
groupdocs/merger.cpython-313-darwin.so
groupdocs/merger.cpython-35m-darwin.so
groupdocs/merger.cpython-36m-darwin.so
groupdocs/merger.cpython-37m-darwin.so
groupdocs/merger.cpython-38-darwin.so
groupdocs/merger.cpython-39-darwin.so
groupdocs/pycore.cpython-310-darwin.so
groupdocs/pycore.cpython-311-darwin.so
groupdocs/pycore.cpython-312-darwin.so
groupdocs/pycore.cpython-313-darwin.so
groupdocs/pycore.cpython-35m-darwin.so
groupdocs/pycore.cpython-36m-darwin.so
groupdocs/pycore.cpython-37m-darwin.so
groupdocs/pycore.cpython-38-darwin.so
groupdocs/pycore.cpython-39-darwin.so
groupdocs/pygc.cpython-310-darwin.so
groupdocs/pygc.cpython-311-darwin.so
groupdocs/pygc.cpython-312-darwin.so
groupdocs/pygc.cpython-313-darwin.so
groupdocs/pygc.cpython-35m-darwin.so
groupdocs/pygc.cpython-36m-darwin.so
groupdocs/pygc.cpython-37m-darwin.so
groupdocs/pygc.cpython-38-darwin.so
groupdocs/pygc.cpython-39-darwin.so
groupdocs/pyreflection.cpython-310-darwin.so
groupdocs/pyreflection.cpython-311-darwin.so
groupdocs/pyreflection.cpython-312-darwin.so
groupdocs/pyreflection.cpython-313-darwin.so
groupdocs/pyreflection.cpython-35m-darwin.so
groupdocs/pyreflection.cpython-36m-darwin.so
groupdocs/pyreflection.cpython-37m-darwin.so
groupdocs/pyreflection.cpython-38-darwin.so
groupdocs/pyreflection.cpython-39-darwin.so
groupdocs/__pyinstaller/__init__.pyi
groupdocs/__pyinstaller/hook-groupdocs.py
groupdocs/assemblies/merger/Aspose.Drawing.Common.dll
groupdocs/assemblies/merger/Aspose.Drawing.dll
groupdocs/assemblies/merger/GroupDocs.Merger.dll
groupdocs/assemblies/merger/Microsoft.DotNet.PlatformAbstractions.dll
groupdocs/assemblies/merger/Microsoft.Extensions.DependencyModel.dll
groupdocs/assemblies/merger/Microsoft.Extensions.Logging.Abstractions.dll
groupdocs/assemblies/merger/Microsoft.Win32.SystemEvents.dll
groupdocs_merger_net-25.3.dist-info/METADATA
groupdocs_merger_net-25.3.dist-info/WHEEL
groupdocs_merger_net-25.3.dist-info/entry_points.txt
groupdocs_merger_net-25.3.dist-info/top_level.txt
groupdocs_merger_net-25.3.dist-info/RECORD
