Metadata-Version: 2.1
Name: groupdocs-merger-net
Version: 25.3
Summary: GroupDocs.Merger for Python via .NET is a powerful API to merge several documents into one, split single document to multiple documents, reorder or replace document pages, change page orientation, manage document protection, render documents as images and more.
Home-page: https://products.groupdocs.com/merger
Author: GroupDocs
License: Other/Proprietary License
Keywords: pdf-merger document-merger image-merger photo-merger zip-merger jpg-merger jpeg-merger merge-pdf merge-word-document merge-excel-files merge-images merge-jpg,combine-pdf combine-word-document combine-excel-files combine-audio combine-mp3 combine-images join-pdf join-mp3 join-images extract-pdf-pages remove-pdf-pages,rotate-pdf pdf-swap-page-order pdf-splitter split-pdf split-pdf-document page-orientation combine-to-pdf combine-jpg-to-pdf merge-word-to-pdf merge-docx-to-pdf
Platform: macos_x86_64
Classifier: Operating System :: Microsoft :: Windows
Classifier: Operating System :: POSIX :: Linux
Classifier: Operating System :: Unix
Classifier: License :: Other/Proprietary License
Classifier: Programming Language :: Python :: 3
Classifier: Programming Language :: Python :: 3 :: Only
Classifier: Programming Language :: Python :: 3.8
Classifier: Programming Language :: Python :: 3.9
Classifier: Topic :: Software Development :: Libraries
Classifier: Topic :: Utilities
Requires-Python: >=3.5,<3.14
